ak_simulator/__init__.py
ak_simulator/__main__.py
ak_simulator/temporal.py
ak_simulator/ak_simulator/conf/ui_simulation_settings.conf
ak_simulator/ak_simulator/conf/ui_simulation_settings_all_test.conf
camera_management_s/__init__.py
camera_management_s/camera_parameters.py
camera_management_s/camera_parameters_selector.py
camera_management_s/test/__init__.py
camera_management_s/test/test_calibration.py
camera_management_s/test/test_camera_parameters.py
data_features_processor/__init__.py
data_features_processor/data_features_config.py
data_features_processor/features_extraction.py
data_features_processor/test/__init__.py
data_features_processor/test/test_data_feature_config.py
data_features_processor/test/test_features_extraction.py
data_features_processor/test/test_features_extraction_mask.py
dataset_management/__init__.py
dataset_management/dataset_config.py
dataset_management/dataset_manager.py
dataset_management/filename_decoder.py
dataset_management/pascal_voc_parser.py
dataset_management/test/__init__.py
dataset_management/test/test_dataset_config.py
dataset_management/test/test_dataset_manager.py
dataset_management/test/test_filename_decoder.py
dataset_management/test/test_pascal_voc_parser.py
dataset_management/test/test_suite_dataset_management.py
depth_estimation_s/__init__.py
depth_estimation_s/depth_estimation_methods.py
depth_estimation_s/depth_estimation_methods_selector.py
depth_estimation_s/test/__init__.py
depth_estimation_s/test/test_depth_estimation.py
depth_estimation_s/test/test_depth_estimation_mask.py
gui_simulation/__init__.py
gui_simulation/about_simulation_window.py
gui_simulation/gui_simulation_config.py
gui_simulation/gui_tab_window.py
gui_simulation/help_simulation_window.py
gui_simulation/assets/icon_app.png
gui_simulation/assets/logo_app.png
gui_simulation/assets/logo_collaborators.png
gui_simulation/assets/logo_grap.png
gui_simulation/assets/logo_help.png
helpers/__init__.py
helpers/helper_filesystem.py
ak_simulator-0.0.9.dist-info/LICENSE
ak_simulator-0.0.9.dist-info/METADATA
ak_simulator-0.0.9.dist-info/WHEEL
ak_simulator-0.0.9.dist-info/top_level.txt
ak_simulator-0.0.9.dist-info/RECORD
