Metadata-Version: 2.1
Name: ak-simulator
Version: 0.0.9
Summary: AK_SIMULATOR that makes it possible to apply different sizing algorithms and allometric yield prediction models to manually labeled color and depth tree images.
Home-page: https://github.com/GRAP-UdL-AT/ak_simulator
Author: Juan Carlos Miranda, Jaume Arno, Jordi Gene-Mola, Spyros Fountas, Eduard Gregorio
Author-email: juancarlos.miranda@udl.cat, jaume.arno@udl.cat, jordi.genemola@udl.cat, sfountas@aua.gr, eduard.gregorio@udl.cat
Project-URL: Bug Tracker, https://github.com/GRAP-UdL-AT/ak_simulator/issues
Classifier: Programming Language :: Python :: 3
Classifier: License :: OSI Approved :: MIT License
Classifier: Operating System :: OS Independent
Requires-Python: >=3.8
License-File: LICENSE
Requires-Dist: pip ==23.2.1
Requires-Dist: bleach ==6.0.0
Requires-Dist: build ==0.10.0
Requires-Dist: certifi ==2022.12.7
Requires-Dist: charset-normalizer ==3.0.1
Requires-Dist: colorama ==0.4.6
Requires-Dist: contourpy ==1.1.0
Requires-Dist: cycler ==0.11.0
Requires-Dist: docutils ==0.19
Requires-Dist: fonttools ==4.40.0
Requires-Dist: idna ==3.4
Requires-Dist: importlib-metadata ==6.0.0
Requires-Dist: importlib-resources ==5.12.0
Requires-Dist: jaraco.classes ==3.2.3
Requires-Dist: joblib ==1.2.0
Requires-Dist: keyring ==23.13.1
Requires-Dist: kiwisolver ==1.4.4
Requires-Dist: lxml ==4.9.2
Requires-Dist: markdown-it-py ==2.2.0
Requires-Dist: matplotlib ==3.7.2
Requires-Dist: mdurl ==0.1.2
Requires-Dist: more-itertools ==9.1.0
Requires-Dist: numpy ==1.24.2
Requires-Dist: opencv-python ==4.7.0.68
Requires-Dist: packaging ==23.0
Requires-Dist: pandas ==1.5.3
Requires-Dist: path ==16.6.0
Requires-Dist: Pillow ==9.4.0
Requires-Dist: pkginfo ==1.9.6
Requires-Dist: Pygments ==2.14.0
Requires-Dist: pyk4a ==1.5.0
Requires-Dist: pyparsing ==3.0.9
Requires-Dist: pyproject-hooks ==1.0.0
Requires-Dist: python-dateutil ==2.8.2
Requires-Dist: python-version ==0.0.2
Requires-Dist: pytz ==2022.7.1
Requires-Dist: pywin32-ctypes ==0.2.0
Requires-Dist: readme-renderer ==37.3
Requires-Dist: requests ==2.28.2
Requires-Dist: requests-toolbelt ==0.10.1
Requires-Dist: rfc3986 ==2.0.0
Requires-Dist: rich ==13.3.1
Requires-Dist: scikit-learn ==1.2.1
Requires-Dist: scipy ==1.10.1
Requires-Dist: six ==1.16.0
Requires-Dist: threadpoolctl ==3.1.0
Requires-Dist: tomli ==2.0.1
Requires-Dist: twine ==4.0.2
Requires-Dist: typing-extensions ==4.5.0
Requires-Dist: urllib3 ==1.26.14
Requires-Dist: webencodings ==0.5.1
Requires-Dist: zipp ==3.14.0
